cloudshell/__init__.py
cloudshell/shell/__init__.py
cloudshell/shell/flows/__init__.py
cloudshell/shell/flows/connectivity/__init__.py
cloudshell/shell/flows/connectivity/abstrace_flow.py
cloudshell/shell/flows/connectivity/basic_flow.py
cloudshell/shell/flows/connectivity/cloud_providers_flow.py
cloudshell/shell/flows/connectivity/devices_flow.py
cloudshell/shell/flows/connectivity/exceptions.py
cloudshell/shell/flows/connectivity/parse_request_service.py
cloudshell/shell/flows/connectivity/simple_flow.py
cloudshell/shell/flows/connectivity/helpers/__init__.py
cloudshell/shell/flows/connectivity/helpers/dict_action_helpers.py
cloudshell/shell/flows/connectivity/helpers/group_cp_actions.py
cloudshell/shell/flows/connectivity/helpers/remove_vlans.py
cloudshell/shell/flows/connectivity/helpers/types.py
cloudshell/shell/flows/connectivity/helpers/vlan_helper.py
cloudshell/shell/flows/connectivity/helpers/vnic_helpers.py
cloudshell/shell/flows/connectivity/models/__init__.py
cloudshell/shell/flows/connectivity/models/connectivity_model.py
cloudshell/shell/flows/connectivity/models/driver_response.py
tests/__init__.py
tests/base.py
tests/conftest.py
tests/test_basic_flow.py
tests/test_cp_flow.py
tests/test_devices_flow.py
tests/test_parse_request_service.py
tests/test_simple_flow.py
tests/helpers/__init__.py
tests/helpers/test_dict_action_helpers.py
tests/helpers/test_grouping_actions.py
tests/helpers/test_remove_vlans.py
tests/helpers/test_vlan_helper.py
tests/helpers/test_vnic_helpers.py
tests/models/__init__.py
tests/models/test_connectivity_model.py
tests/models/test_driver_response.py
cloudshell_shell_connectivity_flow-4.2.0.dist-info/METADATA
cloudshell_shell_connectivity_flow-4.2.0.dist-info/WHEEL
cloudshell_shell_connectivity_flow-4.2.0.dist-info/top_level.txt
cloudshell_shell_connectivity_flow-4.2.0.dist-info/RECORD
