Metadata-Version: 2.1
Name: cloudshell-shell-connectivity-flow
Version: 4.2.0
Summary: QualiSystems Shells Connectivity Flow Package
Home-page: https://www.quali.com/
Author: QualiSystems
Author-email: info@qualisystems.com
Requires-Python: ~=3.9
Requires-Dist: cloudshell-logging ~=2.0
Requires-Dist: pydantic <2.5,>=1.7
Requires-Dist: attrs <23.2,>=22
